shuangchentools/__init__.py
shuangchentools/doc_segment/__init__.py
shuangchentools/doc_segment/doc_segment_by_rule.py
shuangchentools/spider/__init__.py
shuangchentools/spider/selenium.py
shuangchentools/utils/__init__.py
shuangchentools/utils/command.py
shuangchentools/utils/decorators.py
shuangchentools/utils/file.py
shuangchentools/utils/transform.py
shuangchentools-0.0.6.dist-info/METADATA
shuangchentools-0.0.6.dist-info/WHEEL
shuangchentools-0.0.6.dist-info/top_level.txt
shuangchentools-0.0.6.dist-info/RECORD
