Metadata-Version: 2.1
Name: shuangchentools
Version: 0.0.6
Summary: encapsulated some commonly used tools
Home-page: https://github.com/wangtao2001/shuangchentools
Author: shuangchen
Author-email: wangtao.cpu@gmail.com
Requires-Dist: selenium (>=4.15.2)
Requires-Dist: requests (>=2.31.0)
